azure/cognitiveservices/search/customimagesearch/__init__.py
azure/cognitiveservices/search/customimagesearch/_configuration.py
azure/cognitiveservices/search/customimagesearch/_custom_image_search_client.py
azure/cognitiveservices/search/customimagesearch/py.typed
azure/cognitiveservices/search/customimagesearch/version.py
azure/cognitiveservices/search/customimagesearch/models/__init__.py
azure/cognitiveservices/search/customimagesearch/models/_custom_image_search_client_enums.py
azure/cognitiveservices/search/customimagesearch/models/_models.py
azure/cognitiveservices/search/customimagesearch/models/_models_py3.py
azure/cognitiveservices/search/customimagesearch/operations/__init__.py
azure/cognitiveservices/search/customimagesearch/operations/_custom_instance_operations.py
azure_cognitiveservices_search_customimagesearch-0.2.1.dist-info/LICENSE
azure_cognitiveservices_search_customimagesearch-0.2.1.dist-info/METADATA
azure_cognitiveservices_search_customimagesearch-0.2.1.dist-info/WHEEL
azure_cognitiveservices_search_customimagesearch-0.2.1.dist-info/top_level.txt
azure_cognitiveservices_search_customimagesearch-0.2.1.dist-info/RECORD
